MANIFEST.in
README.md
setup.py
opdb/__init__.py
opdb/db.py
opdb/debugger.py
opdb/deobfuscator.py
opdb/log.py
opdb/patcher.py
opdb/test_opdb.py
opdb/test_patcher.py
opdb/test_util.py
opdb/tracer.py
opdb/util.py
opdb.egg-info/PKG-INFO
opdb.egg-info/SOURCES.txt
opdb.egg-info/dependency_links.txt
opdb.egg-info/top_level.txt
opdb/lib/__init__.py
opdb/lib/lnotab.py
opdb/lib/pyc.py
opdb/lib/test_pyc.py
pystack/pystack2.cpp
pystack/pystack3.cpp