Metadata-Version: 2.1
Name: opdb
Version: 0.1.1
Summary: opcode level python debugger
Home-page: https://github.com/ssst0n3/opdb
Author: ssst0n3
Author-email: ssst0n3@gmail.com
License: UNKNOWN
Download-URL: https://github.com/ssst0n3/opdb/releases/download/v0.1/opdb-0.1.tar.gz
Platform: UNKNOWN
Classifier: Programming Language :: Python :: 2
Classifier: Programming Language :: Python :: 3
